CognexNativePy/CognexCommandError.py
CognexNativePy/NativeInterface.py
CognexNativePy/__init__.py
CognexNativePy/utils.py
CognexNativePy/commands/ExecutionAndOnline.py
CognexNativePy/commands/FileAndJob.py
CognexNativePy/commands/Image.py
CognexNativePy/commands/SettingsAndCellsValues.py
CognexNativePy/commands/__init__.py
cognexnativepy-1.0.11.dist-info/licenses/LICENSE
cognexnativepy-1.0.11.dist-info/METADATA
cognexnativepy-1.0.11.dist-info/WHEEL
cognexnativepy-1.0.11.dist-info/top_level.txt
cognexnativepy-1.0.11.dist-info/RECORD
