Metadata-Version: 2.4
Name: CognexNativePy
Version: 1.0.11
Summary: A Python library for communicating with Cognex In-Sight vision systems. Wrapper of the native commands
Home-page: https://github.com/FLo-ABB/CognexNativePy
Author: Florian LOBERT
Classifier: Programming Language :: Python :: 3
Classifier: License :: OSI Approved :: MIT License
Classifier: Operating System :: OS Independent
Classifier: Intended Audience :: Developers
License-File: LICENSE
Dynamic: author
Dynamic: classifier
Dynamic: description
Dynamic: description-content-type
Dynamic: home-page
Dynamic: license-file
Dynamic: summary
